{
    "number": 705,
    "name": "Colimucus",
    "cry": "https://raw.githubusercontent.com/PokeAPI/cries/main/cries/pokemon/latest/705.ogg",
    "form": [
        {
            "name": "normal",
            "types": [
                "dragon"
            ],
            "image": "https://img.pokemondb.net/artwork/large/sliggoo.jpg",
            "base": {
                "hp": 68,
                "attack": 75,
                "defense": 53,
                "spAttack": 83,
                "spDefense": 113,
                "speed": 60
            },
            "description": "Il repousse ses ennemis en s\u00e9cr\u00e9tant un fluide qui dissout tout ce qu\u2019il touche. Suite \u00e0 une d\u00e9g\u00e9n\u00e9rescence de ses yeux, il est aveugle.",
            "abilities": [
                143,
                141,
                218
            ],
            "height": 8,
            "weight": 175
        },
        {
            "name": "hisui",
            "types": [
                "dragon",
                "steel"
            ],
            "image": "https://img.pokemondb.net/artwork/large/sliggoo-hisuian.jpg",
            "base": {
                "hp": 58,
                "attack": 75,
                "defense": 83,
                "spAttack": 83,
                "spDefense": 113,
                "speed": 40
            },
            "description": "Il repousse ses ennemis en s\u00e9cr\u00e9tant un fluide qui dissout tout ce qu\u2019il touche. Suite \u00e0 une d\u00e9g\u00e9n\u00e9rescence de ses yeux, il est aveugle.",
            "abilities": [
                143,
                66,
                218
            ],
            "height": 7,
            "weight": 685
        }
    ]
}