{
    "number": 632,
    "name": "Fermite",
    "cry": "https://raw.githubusercontent.com/PokeAPI/cries/main/cries/pokemon/latest/632.ogg",
    "form": [
        {
            "name": "normal",
            "types": [
                "bug",
                "steel"
            ],
            "image": "https://img.pokemondb.net/artwork/large/durant.jpg",
            "base": {
                "hp": 58,
                "attack": 109,
                "defense": 112,
                "spAttack": 48,
                "spDefense": 48,
                "speed": 109
            },
            "description": "Sa grande m\u00e2choire r\u00e9duit m\u00eame les rochers en miettes. Il se bat avec sa colonie pour prot\u00e9ger ses \u0152ufs des attaques des Dunaconda.",
            "abilities": [
                {
                    "id": 111,
                    "name": "Essaim",
                    "description": "Augmente la puissance des attaques de type Insecte de 50% lorsque le Pok\u00e9mon a moins d'1/3 de ses PV totaux.",
                    "isHidden": false
                },
                {
                    "id": 8,
                    "name": "Agitation",
                    "description": "Augmente l'attaque de 50% mais baisse la pr\u00e9cision de 20%.",
                    "isHidden": false
                },
                {
                    "id": 1,
                    "name": "Absent\u00e9isme",
                    "description": "Le Pok\u00e9mon n'attaque qu'un tour sur deux.",
                    "isHidden": true
                }
            ],
            "height": 3,
            "weight": 330
        }
    ]
}