{
    "number": 170,
    "name": "Loupio",
    "cry": "https://raw.githubusercontent.com/PokeAPI/cries/main/cries/pokemon/latest/170.ogg",
    "form": [
        {
            "name": "normal",
            "types": [
                "water",
                "electrik"
            ],
            "image": "https://img.pokemondb.net/artwork/large/chinchou.jpg",
            "base": {
                "hp": 75,
                "attack": 38,
                "defense": 38,
                "spAttack": 56,
                "spDefense": 56,
                "speed": 67
            },
            "description": "LOUPIO rel\u00e2che des charges \u00e9lectriques positives et n\u00e9gatives de ses deux antennes pour mettre sa proie K.O. Ce POK\u00e9MON illumine ses ampoules \u00e9lectriques pour communiquer avec ses cong\u00e9n\u00e8res.",
            "abilities": [
                {
                    "id": 2,
                    "name": "Absorb Eau",
                    "description": "Les attaques de type Eau re\u00e7ues par le Pok\u00e9mon r\u00e9g\u00e9n\u00e8rent 1/4 de ses PV.",
                    "isHidden": false
                },
                {
                    "id": 165,
                    "name": "Lumiattirance",
                    "description": "Aucun effet en combat",
                    "isHidden": false
                },
                {
                    "id": 3,
                    "name": "Absorb Volt",
                    "description": "Les attaques de type \u00c9lectrik re\u00e7ues par le Pok\u00e9mon r\u00e9g\u00e9n\u00e8rent 1/4 de ses PV.",
                    "isHidden": true
                }
            ],
            "height": 5,
            "weight": 120
        }
    ]
}