{
    "number": 228,
    "name": "Malosse",
    "cry": "https://raw.githubusercontent.com/PokeAPI/cries/main/cries/pokemon/latest/228.ogg",
    "form": [
        {
            "name": "normal",
            "types": [
                "dark",
                "fire"
            ],
            "image": "https://img.pokemondb.net/artwork/large/houndour.jpg",
            "base": {
                "hp": 45,
                "attack": 60,
                "defense": 30,
                "spAttack": 80,
                "spDefense": 50,
                "speed": 65
            },
            "description": "Les MALOSSE chassent en meute organis\u00e9e. Ils communiquent entre eux gr\u00e2ce \u00e0 une s\u00e9rie de petits cris et encerclent ainsi leur proie. L'\u00e9tonnant travail d'\u00e9quipe de ces POK\u00e9MON est sans comparaison.",
            "abilities": [
                {
                    "id": 281,
                    "name": "Torche",
                    "description": "Annule les d\u00e9g\u00e2ts des attaques de type Feu subies et augmente de 50% la puissance des attaques de type Feu lanc\u00e9es.",
                    "isHidden": false
                },
                {
                    "id": 171,
                    "name": "Matinal",
                    "description": "R\u00e9duit le nombre de tours de sommeil du Pok\u00e9mon.",
                    "isHidden": false
                },
                {
                    "id": 273,
                    "name": "Tension",
                    "description": "Emp\u00eache l'adversaire de consommer sa baie.",
                    "isHidden": true
                }
            ],
            "height": 6,
            "weight": 108
        }
    ]
}