{
    "number": 726,
    "name": "Matoufeu",
    "cry": "https://raw.githubusercontent.com/PokeAPI/cries/main/cries/pokemon/latest/726.ogg",
    "form": [
        {
            "name": "normal",
            "types": [
                "fire"
            ],
            "image": "https://img.pokemondb.net/artwork/large/torracat.jpg",
            "base": {
                "hp": 65,
                "attack": 85,
                "defense": 50,
                "spAttack": 80,
                "spDefense": 50,
                "speed": 90
            },
            "description": "Il est tr\u00e8s fier de ses pattes avant muscl\u00e9es, et ne se g\u00eane pas pour le montrer en tordant des barres de fer d\u2019un seul coup de poing.",
            "abilities": [
                {
                    "id": 44,
                    "name": "Brasier",
                    "description": "Augmente la puissance des attaques de type Feu de 50% lorsque le Pok\u00e9mon a moins d'1/3 de ses PV totaux.",
                    "isHidden": false
                },
                {
                    "id": 156,
                    "name": "Intimidation",
                    "description": "Diminue d'un niveau l'attaque du Pok\u00e9mon adverse.",
                    "isHidden": true
                }
            ],
            "height": 7,
            "weight": 250
        }
    ]
}